{"completed": 1, "total": 1, "batch_id": 53, "current_student": "", "current_phase": "", "student_progress": 0.0, "percent": 100, "phase_label": "حفظ النتائج...", "start_time": 1782713661.8786073, "student_times": [105.96492862701416], "completed_students": ["العاب"], "all_student_names": ["العاب"], "archive_all_files": ["1.png", "10.png", "2.png", "3.png", "4.png", "5.png", "6.png", "7.png", "8.png", "9.png", "شرح اللعبة.mp4", "شرح عرض تقدمي.mp4", "نموذج الأولي قبل التعديل .sb3", "نموذج نهائي بعد التعديل .sb3", "هدف ب.docx", "هدف ج.pptx", "Images", "video", "العاب"], "archive_student_map": {"العاب": ["1.png", "10.png", "2.png", "3.png", "4.png", "5.png", "6.png", "7.png", "8.png", "9.png", "شرح اللعبة.mp4", "شرح عرض تقدمي.mp4", "نموذج الأولي قبل التعديل .sb3", "نموذج نهائي بعد التعديل .sb3", "هدف ب.docx", "هدف ج.pptx", "Images", "video", "العاب"]}, "upload_intake": {"submission_noise_flags": [], "upload_diagnostics": {"total_files_uploaded": 1, "total_bytes_uploaded": 36432398, "ignored_files": 0, "ignored_bytes_estimate": 0, "effective_analysis_files": 1, "ignored_path_segment_hits": {}, "ignore_ratio": 0.0, "packaging_recommendation_ar": "يُفضّل تسليم المشروع كملف ZIP واحد مع استبعاد مجلدات Library وTemp وobj وbuild وnode_modules لتقليل الضجيج وتحسين سرعة الرفع واستقرار استخراج الأدلة الآلي.", "auto_ignore_segments": [".ds_store", ".git", ".godot", ".gradle", ".idea", ".vs", "__macosx", "__pycache__", "_build", "bin", "build", "builds", "cachedata", "debug", "deriveddata", "library", "logs", "node_modules", "obj", "packages", "release", "temp", "testresults", "tmp"], "multipart_parts": 1}}, "grading_mode": "deep", "grading_mode_label": "PRO", "finished": true, "failed": false, "final_response": {"success": true, "batch_id": 53, "total_students": 1, "processed": 1, "summary_report_url": "/uploads/reports/batch_summary_53.pdf", "upload_intake": {"submission_noise_flags": [], "upload_diagnostics": {"total_files_uploaded": 1, "total_bytes_uploaded": 36432398, "ignored_files": 0, "ignored_bytes_estimate": 0, "effective_analysis_files": 1, "ignored_path_segment_hits": {}, "ignore_ratio": 0.0, "packaging_recommendation_ar": "يُفضّل تسليم المشروع كملف ZIP واحد مع استبعاد مجلدات Library وTemp وobj وbuild وnode_modules لتقليل الضجيج وتحسين سرعة الرفع واستقرار استخراج الأدلة الآلي.", "auto_ignore_segments": [".ds_store", ".git", ".godot", ".gradle", ".idea", ".vs", "__macosx", "__pycache__", "_build", "bin", "build", "builds", "cachedata", "debug", "deriveddata", "library", "logs", "node_modules", "obj", "packages", "release", "temp", "testresults", "tmp"], "multipart_parts": 1}}}, "cancelled": false}